skore/__init__.py
skore/_config.py
skore/exceptions.py
skore/_externals/__init__.py
skore/_externals/_pandas_accessors.py
skore/_externals/_sklearn_compat.py
skore/_externals/_skrub_compat.py
skore/_sklearn/__init__.py
skore/_sklearn/_base.py
skore/_sklearn/find_ml_task.py
skore/_sklearn/types.py
skore/_sklearn/_comparison/__init__.py
skore/_sklearn/_comparison/feature_importance_accessor.py
skore/_sklearn/_comparison/metrics_accessor.py
skore/_sklearn/_comparison/report.py
skore/_sklearn/_comparison/utils.py
skore/_sklearn/_cross_validation/__init__.py
skore/_sklearn/_cross_validation/data_accessor.py
skore/_sklearn/_cross_validation/feature_importance_accessor.py
skore/_sklearn/_cross_validation/metrics_accessor.py
skore/_sklearn/_cross_validation/report.py
skore/_sklearn/_estimator/__init__.py
skore/_sklearn/_estimator/data_accessor.py
skore/_sklearn/_estimator/feature_importance_accessor.py
skore/_sklearn/_estimator/metrics_accessor.py
skore/_sklearn/_estimator/report.py
skore/_sklearn/_plot/__init__.py
skore/_sklearn/_plot/base.py
skore/_sklearn/_plot/utils.py
skore/_sklearn/_plot/data/__init__.py
skore/_sklearn/_plot/data/table_report.py
skore/_sklearn/_plot/metrics/__init__.py
skore/_sklearn/_plot/metrics/confusion_matrix.py
skore/_sklearn/_plot/metrics/feature_importance_coefficients_display.py
skore/_sklearn/_plot/metrics/metrics_summary_display.py
skore/_sklearn/_plot/metrics/precision_recall_curve.py
skore/_sklearn/_plot/metrics/prediction_error.py
skore/_sklearn/_plot/metrics/roc_curve.py
skore/_sklearn/train_test_split/__init__.py
skore/_sklearn/train_test_split/train_test_split.py
skore/_sklearn/train_test_split/warning/__init__.py
skore/_sklearn/train_test_split/warning/high_class_imbalance_too_few_examples_warning.py
skore/_sklearn/train_test_split/warning/high_class_imbalance_warning.py
skore/_sklearn/train_test_split/warning/random_state_unset_warning.py
skore/_sklearn/train_test_split/warning/shuffle_true_warning.py
skore-0.11.7.dist-info/METADATA
skore-0.11.7.dist-info/WHEEL
skore-0.11.7.dist-info/licenses/LICENSE
skore-0.11.7.dist-info/RECORD
