Metadata-Version: 2.4
Name: skore
Version: 0.11.7
Summary: 𝗢𝘄𝗻 𝗬𝗼𝘂𝗿 𝗗𝗮𝘁𝗮 𝗦𝗰𝗶𝗲𝗻𝗰𝗲. Skore's open-source Python library accelerates ML model development with automated evaluation reports, smart methodological guidance, and comprehensive cross-validation analysis.
Project-URL: Homepage, https://probabl.ai
Project-URL: Repository, https://github.com/probabl-ai/skore
Project-URL: Download, https://pypi.org/project/skore/#files
Project-URL: Issues, https://github.com/probabl-ai/skore/issues
Project-URL: Release notes, https://github.com/probabl-ai/skore/releases
Maintainer-email: skore developers <skore@signal.probabl.ai>
License-Expression: MIT
License-File: LICENSE
Classifier: Development Status :: 3 - Alpha
Classifier: Intended Audience :: Developers
Classifier: Intended Audience :: Science/Research
Classifier: Operating System :: MacOS
Classifier: Operating System :: Microsoft :: Windows
Classifier: Operating System :: POSIX
Classifier: Operating System :: Unix
Classifier: Programming Language :: Python
Classifier: Programming Language :: Python :: 3
Classifier: Programming Language :: Python :: 3.10
Classifier: Programming Language :: Python :: 3.11
Classifier: Programming Language :: Python :: 3.12
Classifier: Programming Language :: Python :: 3.13
Classifier: Topic :: Scientific/Engineering
Classifier: Topic :: Software Development
Requires-Python: >=3.10
Requires-Dist: anywidget
Requires-Dist: ipython
Requires-Dist: ipywidgets
Requires-Dist: joblib
Requires-Dist: matplotlib
Requires-Dist: numpy
Requires-Dist: pandas
Requires-Dist: plotly
Requires-Dist: rich
Requires-Dist: scikit-learn
Requires-Dist: seaborn
Requires-Dist: skore[local]
Requires-Dist: skrub
Provides-Extra: dev
Requires-Dist: ipykernel; extra == 'dev'
Requires-Dist: nbformat; extra == 'dev'
Provides-Extra: hub
Requires-Dist: skore-hub-project>=0.0.10; extra == 'hub'
Provides-Extra: local
Requires-Dist: skore-local-project>=0.0.4; extra == 'local'
Provides-Extra: sphinx
Requires-Dist: altair; extra == 'sphinx'
Requires-Dist: kaleido; extra == 'sphinx'
Requires-Dist: numpydoc; extra == 'sphinx'
Requires-Dist: plotly<7,>=6; extra == 'sphinx'
Requires-Dist: polars; extra == 'sphinx'
Requires-Dist: pydata-sphinx-theme; extra == 'sphinx'
Requires-Dist: seaborn; extra == 'sphinx'
Requires-Dist: skrub; extra == 'sphinx'
Requires-Dist: sphinx-autosummary-accessors; extra == 'sphinx'
Requires-Dist: sphinx-copybutton; extra == 'sphinx'
Requires-Dist: sphinx-design; extra == 'sphinx'
Requires-Dist: sphinx-gallery; extra == 'sphinx'
Requires-Dist: sphinx-tabs; extra == 'sphinx'
Requires-Dist: sphinx<8.2.0; extra == 'sphinx'
Requires-Dist: xgboost-cpu; extra == 'sphinx'
Provides-Extra: sphinx-base
Requires-Dist: altair; extra == 'sphinx-base'
Requires-Dist: kaleido; extra == 'sphinx-base'
Requires-Dist: numpydoc; extra == 'sphinx-base'
Requires-Dist: plotly<7,>=6; extra == 'sphinx-base'
Requires-Dist: pydata-sphinx-theme; extra == 'sphinx-base'
Requires-Dist: seaborn; extra == 'sphinx-base'
Requires-Dist: skrub; extra == 'sphinx-base'
Requires-Dist: sphinx-autosummary-accessors; extra == 'sphinx-base'
Requires-Dist: sphinx-copybutton; extra == 'sphinx-base'
Requires-Dist: sphinx-design; extra == 'sphinx-base'
Requires-Dist: sphinx-gallery; extra == 'sphinx-base'
Requires-Dist: sphinx-tabs; extra == 'sphinx-base'
Requires-Dist: sphinx<8.2.0; extra == 'sphinx-base'
Requires-Dist: xgboost-cpu; extra == 'sphinx-base'
Provides-Extra: sphinx-lts-cpu
Requires-Dist: altair; extra == 'sphinx-lts-cpu'
Requires-Dist: kaleido; extra == 'sphinx-lts-cpu'
Requires-Dist: numpydoc; extra == 'sphinx-lts-cpu'
Requires-Dist: plotly<7,>=6; extra == 'sphinx-lts-cpu'
Requires-Dist: polars-lts-cpu; extra == 'sphinx-lts-cpu'
Requires-Dist: pydata-sphinx-theme; extra == 'sphinx-lts-cpu'
Requires-Dist: seaborn; extra == 'sphinx-lts-cpu'
Requires-Dist: skrub; extra == 'sphinx-lts-cpu'
Requires-Dist: sphinx-autosummary-accessors; extra == 'sphinx-lts-cpu'
Requires-Dist: sphinx-copybutton; extra == 'sphinx-lts-cpu'
Requires-Dist: sphinx-design; extra == 'sphinx-lts-cpu'
Requires-Dist: sphinx-gallery; extra == 'sphinx-lts-cpu'
Requires-Dist: sphinx-tabs; extra == 'sphinx-lts-cpu'
Requires-Dist: sphinx<8.2.0; extra == 'sphinx-lts-cpu'
Requires-Dist: xgboost-cpu; extra == 'sphinx-lts-cpu'
Provides-Extra: test
Requires-Dist: polars; extra == 'test'
Requires-Dist: pre-commit; extra == 'test'
Requires-Dist: pyarrow; extra == 'test'
Requires-Dist: pytest; extra == 'test'
Requires-Dist: pytest-cov; extra == 'test'
Requires-Dist: pytest-order; extra == 'test'
Requires-Dist: pytest-randomly; extra == 'test'
Requires-Dist: pytest-xdist; extra == 'test'
Requires-Dist: scipy-stubs; extra == 'test'
Requires-Dist: skrub; extra == 'test'
Requires-Dist: xdoctest; extra == 'test'
Provides-Extra: test-base
Requires-Dist: pre-commit; extra == 'test-base'
Requires-Dist: pytest; extra == 'test-base'
Requires-Dist: pytest-cov; extra == 'test-base'
Requires-Dist: pytest-order; extra == 'test-base'
Requires-Dist: pytest-randomly; extra == 'test-base'
Requires-Dist: pytest-xdist; extra == 'test-base'
Requires-Dist: scipy-stubs; extra == 'test-base'
Requires-Dist: skrub; extra == 'test-base'
Requires-Dist: xdoctest; extra == 'test-base'
Provides-Extra: test-lts-cpu
Requires-Dist: polars-lts-cpu; extra == 'test-lts-cpu'
Requires-Dist: pre-commit; extra == 'test-lts-cpu'
Requires-Dist: pytest; extra == 'test-lts-cpu'
Requires-Dist: pytest-cov; extra == 'test-lts-cpu'
Requires-Dist: pytest-order; extra == 'test-lts-cpu'
Requires-Dist: pytest-randomly; extra == 'test-lts-cpu'
Requires-Dist: pytest-xdist; extra == 'test-lts-cpu'
Requires-Dist: scipy-stubs; extra == 'test-lts-cpu'
Requires-Dist: skrub; extra == 'test-lts-cpu'
Requires-Dist: xdoctest; extra == 'test-lts-cpu'
